fastid-0.0.5.dist-info/METADATA
fastid-0.0.5.dist-info/WHEEL
fastid/__init__.py
fastid/__init__.pyi
fastid/py.typed
fastid/fastid.pypy37-pp73-arm-linux-gnu.so
fastid-0.0.5.dist-info/RECORD
